tritium_remote-1.4.1.dist-info/METADATA
tritium_remote-1.4.1.dist-info/WHEEL
tritium_remote-1.4.1.dist-info/license_files/LICENSE-MIT
tritium_remote/__init__.py
tritium_remote/tritium_remote.cpython-310-x86_64-linux-gnu.so
tritium_remote-1.4.1.dist-info/RECORD
