Metadata-Version: 2.1
Name: tritium-remote
Version: 1.4.1
Classifier: Programming Language :: Rust
Classifier: Programming Language :: Python :: Implementation :: CPython
Classifier: Programming Language :: Python :: Implementation :: PyPy
License-File: LICENSE-MIT
Summary: A library for connecting to remote Robots running TritiumOS
License: MIT OR Apache-2.0
Requires-Python: >=3.7
Project-URL: homepage, https://www.engineeredarts.co.uk/software/tritium/
Project-URL: documentation, https://tritiumrobot.cloud/docs/
